nasdaq_provider/__init__.py
nasdaq_provider/provider.py
pynecore_nasdaq_provider-0.1.2.dist-info/licenses/LICENSE
pynecore_nasdaq_provider-0.1.2.dist-info/METADATA
pynecore_nasdaq_provider-0.1.2.dist-info/WHEEL
pynecore_nasdaq_provider-0.1.2.dist-info/entry_points.txt
pynecore_nasdaq_provider-0.1.2.dist-info/top_level.txt
pynecore_nasdaq_provider-0.1.2.dist-info/RECORD
