Metadata-Version: 2.4
Name: pynecore-nasdaq-provider
Version: 0.1.2
Summary: Nasdaq data provider plugin for PyneCore
Author-email: Mahadi Hassan <mh@mahadihassan.com>
License: MIT
Project-URL: Homepage, https://github.com/itsmahadi007/pynecore-nasdaq-provider
Project-URL: Repository, https://github.com/itsmahadi007/pynecore-nasdaq-provider
Project-URL: Issues, https://github.com/itsmahadi007/pynecore-nasdaq-provider/issues
Project-URL: Documentation, https://github.com/itsmahadi007/pynecore-nasdaq-provider#readme
Keywords: trading,finance,data,provider,pynecore
Classifier: Development Status :: 3 - Alpha
Classifier: Intended Audience :: Developers
Classifier: Environment :: Plugins
Classifier: License :: OSI Approved :: MIT License
Classifier: Programming Language :: Python :: 3
Classifier: Programming Language :: Python :: 3.8
Classifier: Programming Language :: Python :: 3.9
Classifier: Programming Language :: Python :: 3.10
Classifier: Programming Language :: Python :: 3.11
Classifier: Programming Language :: Python :: 3.12
Classifier: Topic :: Office/Business :: Financial
Classifier: Topic :: Scientific/Engineering :: Information Analysis
Requires-Python: >=3.8
License-File: LICENSE
Requires-Dist: pynesys-pynecore>=6.1.2
Provides-Extra: dev
Requires-Dist: pytest>=6.0; extra == "dev"
Requires-Dist: pytest-cov>=2.0; extra == "dev"
Requires-Dist: black>=21.0; extra == "dev"
Requires-Dist: isort>=5.0; extra == "dev"
Requires-Dist: flake8>=3.8; extra == "dev"
Requires-Dist: mypy>=0.800; extra == "dev"
Dynamic: license-file
